sbiqer/__init__.py
sbiqer/config/PathConfig.py
sbiqer/config/__init__.py
sbiqer/entity/BaseEntity.py
sbiqer/entity/__init__.py
sbiqer/exception/ConfigException.py
sbiqer/exception/SbiqerException.py
sbiqer/exception/__init__.py
sbiqer/log/BaseLogger.py
sbiqer/log/ErrorLogger.py
sbiqer/log/InfoLogger.py
sbiqer/log/WarningLogger.py
sbiqer/log/__init__.py
sbiqer/parser/BaseParser.py
sbiqer/parser/__init__.py
sbiqer/requester/BaseRequester.py
sbiqer/requester/__init__.py
sbiqer/schedule/BaseSchedule.py
sbiqer/schedule/__init__.py
sbiqer/test/__init__.py
sbiqer/test/exceptionTest.py
sbiqer/threadpool/ThreadPool.py
sbiqer/threadpool/__init__.py
sbiqer/util/BaseUtil.py
sbiqer/util/ConfigLoader.py
sbiqer/util/MultUtil.py
sbiqer/util/SaveUtil.py
sbiqer/util/__init__.py
sbiqer-0.4.dist-info/METADATA
sbiqer-0.4.dist-info/WHEEL
sbiqer-0.4.dist-info/top_level.txt
sbiqer-0.4.dist-info/RECORD
